gift_card_crawler/__init__.py
gift_card_crawler/admin.py
gift_card_crawler/apps.py
gift_card_crawler/crawlers.py
gift_card_crawler/models.py
gift_card_crawler/tests.py
gift_card_crawler/utils.py
gift_card_crawler/views.py
gift_card_crawler/migrations/__init__.py
gift_card_crawler/static/gift_card_crawler/css/gift_card_crawler.css
gift_card_crawler/static/gift_card_crawler/js/gift_card_crawler.js
gift_card_crawler/templates/gift_card_crawler/admin/cards_datatable.html
gift_card_crawler/templates/gift_card_crawler/admin/change_form.html
django_gift_card_crawler-1.0.0.dist-info/LICENSE
django_gift_card_crawler-1.0.0.dist-info/METADATA
django_gift_card_crawler-1.0.0.dist-info/WHEEL
django_gift_card_crawler-1.0.0.dist-info/top_level.txt
django_gift_card_crawler-1.0.0.dist-info/RECORD
