Metadata-Version: 2.1
Name: django-gift-card-crawler
Version: 1.0.0
Summary: Crawl gift card links and extract card and serial number
Home-page: https://github.com/imankarimi/django-gift-card-crawler
Author: Iman Karimi
Author-email: imankarimi.mail@gmail.com
License: MIT License
Classifier: Environment :: Web Environment
Classifier: Framework :: Django
Classifier: Framework :: Django :: 3.2
Classifier: Framework :: Django :: 4.0
Classifier: Intended Audience :: Developers
Classifier: License :: OSI Approved :: MIT License
Classifier: Programming Language :: Python
Classifier: Programming Language :: Python :: 2.7
Classifier: Programming Language :: Python :: 3.2
Classifier: Programming Language :: Python :: 3.3
Classifier: Programming Language :: Python :: 3.4
Classifier: Programming Language :: Python :: 3.5
Classifier: Programming Language :: Python :: 3.6
Classifier: Programming Language :: Python :: 3.7
Classifier: Programming Language :: Python :: 3.8
Classifier: Environment :: Web Environment
Classifier: Topic :: Software Development
Requires-Python: >=2.7
License-File: LICENSE
Requires-Dist: Django
Requires-Dist: bs4
Requires-Dist: lxml
Requires-Dist: requests
Requires-Dist: pandas
Requires-Dist: xlrd
